oy/__init__.py
oy/exceptions.py
oy/provider.py
oy/request.py
oy/response.py
oy/serializers.py
oy/urls.py
oy/core/__init__.py
oy/core/exceptions.py
oy/core/provider.py
oy/core/remote_call.py
oy/core/request.py
oy/core/response.py
test/core/__init__.py
test/core/test_provider.py
test/core/test_remote_call.py
test/core/test_request.py
test/core/test_response.py
oy_client-0.1.4.1.dist-info/LICENSE.md
oy_client-0.1.4.1.dist-info/METADATA
oy_client-0.1.4.1.dist-info/WHEEL
oy_client-0.1.4.1.dist-info/top_level.txt
oy_client-0.1.4.1.dist-info/RECORD
