Metadata-Version: 2.1
Name: oy-client
Version: 0.1.4.1
Summary: Unofficial Oy Client library for Python
Home-page: https://github.com/vousmeevoyez/oy-client
Author: Kelvin Desman
Author-email: kelvindsmn@gmail.com
License: UNKNOWN
Platform: UNKNOWN
Classifier: Programming Language :: Python :: 3
Classifier: License :: OSI Approved :: MIT License
Classifier: Operating System :: OS Independent
Requires-Python: >=3.6
Requires-Dist: requests
